mcpit/__init__.py
mcpit/__main__.py
mcpit/weaving.py
mcpit-1.1.dist-info/LICENSE
mcpit-1.1.dist-info/METADATA
mcpit-1.1.dist-info/WHEEL
mcpit-1.1.dist-info/entry_points.txt
mcpit-1.1.dist-info/top_level.txt
mcpit-1.1.dist-info/RECORD
