Metadata-Version: 2.1
Name: mcpit
Version: 1.1
Summary: A texture pack tool for the Minecraft: Pi Edition: Reborn mod.
Home-page: https://github.com/mcpiscript
Author: mcpiscript
Author-email: mcpiscript@gmail.com
Maintainer: Alexey Pavlov
Maintainer-email: pezleha@duck.com
License: UNKNOWN
Platform: UNKNOWN
Classifier: License :: OSI Approved :: GNU Affero General Public License v3 or later (AGPLv3+)
Requires-Dist: click
Requires-Dist: pillow
